hintedi/__init__.py
hintedi/hinted_dependency_injector.py
HinteDI-0.3.2.dist-info/LICENSE
HinteDI-0.3.2.dist-info/METADATA
HinteDI-0.3.2.dist-info/WHEEL
HinteDI-0.3.2.dist-info/top_level.txt
HinteDI-0.3.2.dist-info/RECORD
