Metadata-Version: 2.1
Name: HinteDI
Version: 0.3.2
Summary: A simple dependency injector based on type hints
Author-email: Eetu Asikainen <eetu.asikainen1204@gmail.com>
Project-URL: Homepage, https://github.com/EddieTheCubeHead/HinteDI
Project-URL: Bug Tracker, https://github.com/EddieTheCubeHead/HinteDI/issues
Keywords: dependency injection,DI
Classifier: Development Status :: 4 - Beta
Classifier: Intended Audience :: Developers
Classifier: License :: OSI Approved :: MIT License
Classifier: Operating System :: OS Independent
Requires-Python: >=3.10
License-File: LICENSE
